sba/__init__.py
sba/cameras.py
sba/crsm.py
sba/drivers.py
sba/errors.py
sba/info.py
sba/options.py
sba/points.py
sba/projections.py
sba/quaternions.py
sba/routines.py
sba/version.py
sba-1.6.9.data/scripts/eucsbademo.py
sba-1.6.9.dist-info/LICENSE
sba-1.6.9.dist-info/METADATA
sba-1.6.9.dist-info/WHEEL
sba-1.6.9.dist-info/dependency_links.txt
sba-1.6.9.dist-info/top_level.txt
sba-1.6.9.dist-info/RECORD
