Metadata-Version: 2.1
Name: sba
Version: 1.6.9
Summary: Python wrapper for Lourakis' sparse bundle adjustment C library
Home-page: https://bitbucket.org/devangel77b/python-sba
Author: Dennis Evangelista
Author-email: Dennis Evangelista <devangel77b@gmail.com>
License: GNU GPLv3
Project-URL: Homepage, https://bitbucket.org/devangel77b/python-sba
Project-URL: Bug Tracker, https://bitbucket.org/devangel77b/python-sba/issues
Keywords: SBA,sparse bundle adjustment,calibration,camera,camera calibration,photogrammetry
Classifier: Development Status :: 3 - Alpha
Classifier: Programming Language :: Python :: 2.7
Classifier: License :: OSI Approved :: GNU General Public License v3 (GPLv3)
Classifier: Topic :: Scientific/Engineering
Classifier: Topic :: Multimedia :: Video
Classifier: Topic :: Multimedia :: Graphics
Classifier: Topic :: Multimedia :: Graphics :: 3D Modeling
Classifier: Topic :: Multimedia :: Graphics :: Capture :: Digital Camera
Classifier: Operating System :: POSIX :: Linux
Classifier: Operating System :: OS Independent
Classifier: Intended Audience :: Science/Research
Requires-Python: >=3.7
License-File: LICENSE
Requires-Dist: numpy (>=1.12)
